dnsstamps/__init__.py
dnsstamps/option.py
dnsstamps/parameter.py
dnsstamps/protocol.py
dnsstamps/formatter/__init__.py
dnsstamps/formatter/formatter.py
dnsstamps/generator/__init__.py
dnsstamps/generator/generator.py
dnsstamps/parser/__init__.py
dnsstamps/parser/parser.py
dnsstamps/parser/state.py
dnsstamps-1.4.1.data/scripts/dnsstamp.py
dnsstamps-1.4.1.dist-info/licenses/LICENSE
test/__init__.py
test/formatter/__init__.py
test/formatter/test_formatter.py
test/generator/__init__.py
test/generator/test_generator.py
test/parser/__init__.py
test/parser/test_parser.py
dnsstamps-1.4.1.dist-info/METADATA
dnsstamps-1.4.1.dist-info/WHEEL
dnsstamps-1.4.1.dist-info/top_level.txt
dnsstamps-1.4.1.dist-info/RECORD
