Metadata-Version: 2.4
Name: dnsstamps
Version: 1.4.1
Summary: Create and parse DNS stamps with ease.
Home-page: https://github.com/chrisss404/python-dnsstamps
Author: Christian Hofer
Author-email: chrisss404@gmail.com
Classifier: Programming Language :: Python :: 3
Classifier: License :: OSI Approved :: MIT License
Classifier: Operating System :: OS Independent
License-File: LICENSE
Dynamic: author
Dynamic: author-email
Dynamic: classifier
Dynamic: description
Dynamic: description-content-type
Dynamic: home-page
Dynamic: license-file
Dynamic: summary
